{
  "eventName": "Conference 2025",
  "eventSubtitle": "Technology and Innovation for the Future",
  "eventDate": "2025-12-15",
  "eventTime": "10:00",
  "eventEndTime": "17:00",
  "eventLocation": "COEX Convention Center, Seoul",
  "eventDescription": "Conference 2025 is a technology conference featuring industry-leading experts. We share the latest technology trends and innovative ideas while providing networking opportunities.",
  "registrationUrl": "https://example.com/register",
  "registrationButtonImage": "assets/images/register-button.svg",
  "registrationButtonAlt": "Register Now",
  "countdownTarget": "2025-12-15T09:00:00+09:00",
  "heroBackgroundImage": "assets/images/hero-bg.svg",
  "sectionImages": {
    "about": [
      "assets/images/sections/about-1.svg",
      "assets/images/sections/about-2.svg"
    ],
    "events": [
      "assets/images/sections/events-1.svg",
      "assets/images/sections/events-2.svg",
      "assets/images/sections/events-3.svg"
    ],
    "info": [
      "assets/images/sections/info-1.svg",
      "assets/images/sections/info-2.svg"
    ],
    "location": [
      "assets/images/sections/location-1.svg",
      "assets/images/sections/location-2.svg",
      "assets/images/sections/location-3.svg",
      "assets/images/sections/location-4.svg"
    ]
  }
}
